[
  {
    "list": true,
    "name": "Projects",
    "path": "/Projects"
  },
  {
    "name": "Project Euler",
    "pars": ["page/:page"],
    "path": "/Projects/ProjectEuler"
  },
  {
    "icon": ["fab", "react"],
    "name": "Data Generator",
    "path": "/Projects/DataGenerator"
  },
  {
    "icon": ["fab", "html5"],
    "name": "Travel Agency",
    "path": "/Projects/TravelAgency"
  },
  {
    "icon": "chart-bar",
    "name": "React D3",
    "path": "/Projects/ReactD3"
  },
  {
    "icon": "chart-bar",
    "name": "Breaking Bad API",
    "path": "/Projects/BreakingBadAPI"
  },
  {
    "icon": "chart-bar",
    "name": "World Population",
    "path": "/Projects/WorldPopulation"
  },
  {
    "icon": "globe",
    "name": "World Map",
    "path": "/Projects/WorldMap"
  },
  {
    "list": true,
    "name": "Snippets",
    "path": "/Snippets"
  },
  {
    "name": "Coding on my Phone",
    "path": "/Snippets/CodingOnMyPhone"
  },
  {
    "name": "Typescript",
    "path": "/Snippets/Typescript"
  },
  {
    "name": "Jest and @testing-library",
    "path": "/Snippets/Jest"
  },
  {
    "icon": ["fab", "css3"],
    "name": "Display Props",
    "path": "/Snippets/DisplayProps"
  },
  {
    "icon": ["fab", "css3"],
    "name": "Box Model JS",
    "path": "/Snippets/BoxModelJS"
  },
  {
    "icon": ["fab", "css3"],
    "name": "Flex Box",
    "path": "/Snippets/FlexBox"
  },
  {
    "icon": ["fab", "css3"],
    "name": "Grid",
    "path": "/Snippets/Grid"
  },
  {
    "icon": ["fab", "react"],
    "name": "Hooks",
    "path": "/Snippets/Hooks"
  },
  {
    "list": true,
    "name": "About",
    "path": "/About"
  },
  {
    "name": "Contact",
    "path": "/About/Contact"
  },
  {
    "name": "Resume",
    "path": "/About/Resume"
  },
  {
    "name": "Sitemap",
    "path": "/About/Sitemap"
  }
]